pony_portal_gun/__init__.py
pony_portal_gun/__main__.py
pony_portal_gun/main.py
pony_portal_gun-0.1.0.dist-info/entry_points.txt
pony_portal_gun-0.1.0.dist-info/WHEEL
pony_portal_gun-0.1.0.dist-info/METADATA
pony_portal_gun-0.1.0.dist-info/RECORD
